UdCal/__init__.py
UdCal/calculator.py
UdCal-1.0.0.dist-info/LICENCE
UdCal-1.0.0.dist-info/METADATA
UdCal-1.0.0.dist-info/WHEEL
UdCal-1.0.0.dist-info/top_level.txt
UdCal-1.0.0.dist-info/RECORD
